akash_package/__init__.py
akash_package/main.py
akash_package-0.1.dist-info/METADATA
akash_package-0.1.dist-info/WHEEL
akash_package-0.1.dist-info/top_level.txt
akash_package-0.1.dist-info/RECORD
